[
  {
    "gambar": "<img src='gambar/ps2.jpg'>",
    "nama": "PS 2 Harddisk 64gb",
    "harga": "Rp.900.000,-"
  },
  {
    "gambar": "<img src='gambar/ps3.jpg'>",
    "nama": "PS 3 Blue Edition",
    "harga": "Rp.1.900.000,-"
  },
  {
    "gambar": "<img src='gambar/ps4.jpg'>",
    "nama": "PS 4 Final Fantasy Edition",
    "harga": "Rp,3.900.000,-"
  },
  {
    "gambar": "<img src='gambar/psp.jpg'>",
    "nama": "PSP 3000 Black Edition ",
    "harga": "Rp.1.500.000,-"
  },
  {
    "gambar": "<img src='gambar/psvita.jpg'>",
    "nama": "PS Vita Slim",
    "harga": "Rp.2.500.000,-"
  },
  {
    "gambar": "<img src='gambar/pspgo.JPG' >",
    "nama": "PSP GO",
    "harga": "Rp.1.000.000,-"
  },
  {
    "gambar": "<img src='gambar/nintendo3ds.jpg'>",
    "nama": "Nintendo 3ds Edition Mario",
    "harga": "Rp.2.200.000,-"
  },
  {
    "gambar": "<img src='gambar/nintendoswitch.jpg'>",
    "nama": "Nintendo Switch",
    "harga": "Rp.4.300.000,-"
  },
  {
    "gambar": "<img src='gambar/ps2.jpg'>",
    "nama": "Nintendo WII",
    "harga": "Rp.1.500.000,-"
  }
]